moldo/__init__.py
moldo/cli.py
moldo/decorators.py
moldo/moldoi.py
moldo/api/__init__.py
moldo/api/server.py
moldo/core/MoldoEntry.py
moldo/core/MoldoLexer.py
moldo/core/MoldoParser.py
moldo/core/MoldoParserListener.py
moldo/core/MoldoParserVisitor.py
moldo/core/__init__.py
moldo-0.4.0.dist-info/licenses/LICENSE
moldo-0.4.0.dist-info/METADATA
moldo-0.4.0.dist-info/WHEEL
moldo-0.4.0.dist-info/entry_points.txt
moldo-0.4.0.dist-info/top_level.txt
moldo-0.4.0.dist-info/RECORD
