Metadata-Version: 2.4
Name: moldo
Version: 0.4.0
Summary: A visual programming language that compiles to Python
Home-page: https://github.com/GracePeterMutiibwa/moldo
Author: Mutiibwa Grace Peter
Author-email: gracepetermutiibwa@gmail.com
License: MIT
Classifier: Development Status :: 3 - Alpha
Classifier: Intended Audience :: Education
Classifier: Programming Language :: Python :: 3
Classifier: Programming Language :: Python :: 3.8
Classifier: Programming Language :: Python :: 3.9
Classifier: Programming Language :: Python :: 3.10
Classifier: Programming Language :: Python :: 3.11
Classifier: Topic :: Software Development :: Libraries :: Python Modules
Classifier: Topic :: Software Development :: Compilers
Classifier: Topic :: Education
Requires-Python: >=3.8
License-File: LICENSE
Requires-Dist: antlr4-python3-runtime>=4.13.1
Requires-Dist: typing-extensions>=4.0.0
Requires-Dist: uvicorn>=0.34.2
Requires-Dist: fastapi>=0.109.2
Dynamic: author
Dynamic: author-email
Dynamic: classifier
Dynamic: description
Dynamic: description-content-type
Dynamic: home-page
Dynamic: license
Dynamic: license-file
Dynamic: requires-dist
Dynamic: requires-python
Dynamic: summary
